trajvis/__init__.py
trajvis/vis.py
trajvis-0.0.1.dist-info/METADATA
trajvis-0.0.1.dist-info/WHEEL
trajvis-0.0.1.dist-info/licenses/LICENSE
trajvis-0.0.1.dist-info/RECORD
