Metadata-Version: 2.4
Name: trajvis
Version: 0.0.1
Summary: Toolbox to visualize trajectories
Project-URL: Homepage, https://github.com/kylekam/trajectoryvis
Project-URL: Issues, https://github.com/kylekam/trajectoryvis/issues
Author-email: Kyle Kam <kamkyl196@gmail.com>
License: MIT
License-File: LICENSE
Classifier: Operating System :: OS Independent
Classifier: Programming Language :: Python :: 3
Requires-Python: >=3.10
Requires-Dist: imageio>=2.37.0
Requires-Dist: matplotlib>=3.10.1
Requires-Dist: numpy>=2.2.3
Requires-Dist: tilemapbase>=0.4.7
Requires-Dist: tqdm>=4.67.1
